{
  "BTCUSDT": "below",
  "ETHUSDT": "below",
  "SOLUSDT": "below",
  "TAOUSDT": "below",
  "XRPUSDT": "below",
  "ZECUSDT": "below",
  "WLDUSDT": "above",
  "BNBUSDT": "below",
  "TRXUSDT": "below",
  "NIGHTUSDT": "below",
  "DOGEUSDT": "below",
  "NEARUSDT": "below",
  "AVAXUSDT": "below",
  "SUIUSDT": "below",
  "ADAUSDT": "below",
  "ENAUSDT": "below",
  "XLMUSDT": "below",
  "AAVEUSDT": "above",
  "XAUTUSDT": "below",
  "LINKUSDT": "below",
  "PAXGUSDT": "below",
  "PEPEUSDT": "below",
  "UNIUSDT": "touching",
  "LTCUSDT": "below",
  "ASTERUSDT": "below",
  "ONDOUSDT": "below",
  "BCHUSDT": "below",
  "DEXEUSDT": "above",
  "HBARUSDT": "below",
  "FILUSDT": "below",
  "DOTUSDT": "below",
  "RENDERUSDT": "below",
  "ICPUSDT": "below",
  "APTUSDT": "below",
  "WLFIUSDT": "above",
  "POLUSDT": "below",
  "JSTUSDT": "below",
  "ARBUSDT": "below",
  "ETCUSDT": "below",
  "ALGOUSDT": "below",
  "SHIBUSDT": "below",
  "ATOMUSDT": "below",
  "MORPHOUSDT": "below",
  "SKYUSDT": "below",
  "QNTUSDT": "below",
  "NEXOUSDT": "below"
}